hqitc/__init__.py
hqitc/cli.py
hqitc/color.py
hqitc/encoder.py
hqitc/main.py
hqitc/multiscale.py
hqitc/utils.py
hqitc-0.1.1.dist-info/METADATA
hqitc-0.1.1.dist-info/WHEEL
hqitc-0.1.1.dist-info/entry_points.txt
hqitc-0.1.1.dist-info/licenses/LICENSE
hqitc-0.1.1.dist-info/RECORD
